spamrefiner/__init__.py
spamrefiner/client.py
spamrefiner/types.py
spamrefiner/__pycache__/__init__.cpython-39.pyc
spamrefiner/__pycache__/client.cpython-39.pyc
spamrefiner/__pycache__/types.cpython-39.pyc
spamrefiner-0.0.2.dist-info/LICENSE
spamrefiner-0.0.2.dist-info/METADATA
spamrefiner-0.0.2.dist-info/WHEEL
spamrefiner-0.0.2.dist-info/top_level.txt
spamrefiner-0.0.2.dist-info/RECORD
