Metadata-Version: 2.1
Name: spamrefiner
Version: 0.0.2
Summary: SpamRefiner API Wrapper
Home-page: https://github.com/SpamRefiner/srAPI
Author: The Codents
Author-email: info@thecodents.org
License: License :: OSI Approved :: GNU Lesser General Public License v3 (LGPLv3)
Platform: UNKNOWN
Classifier: Development Status :: 4 - Beta
Classifier: Programming Language :: Python :: 3.6
Classifier: Programming Language :: Python :: 3.7
Classifier: Programming Language :: Python :: Implementation :: CPython
Classifier: Typing :: Typed
Requires-Python: >=3.6
Requires-Dist: requests (>=2.20)
